pyhedrals/__init__.py
pyhedrals/pyhedrals.py
pyhedrals-0.2.0.dist-info/LICENSE
pyhedrals-0.2.0.dist-info/METADATA
pyhedrals-0.2.0.dist-info/WHEEL
pyhedrals-0.2.0.dist-info/top_level.txt
pyhedrals-0.2.0.dist-info/RECORD
