Metadata-Version: 2.1
Name: pyhedrals
Version: 0.2.0
Summary: A library for evaluating tabletop dice roll expressions
Home-page: https://github.com/StarlitGhost/pyhedrals
Author: StarlitGhost
Author-email: pyhedrals@starlitghost.xyz
License: UNKNOWN
Platform: UNKNOWN
Classifier: Development Status :: 3 - Alpha
Classifier: Programming Language :: Python :: 3
Classifier: Programming Language :: Python :: 3.6
Classifier: Programming Language :: Python :: 3.7
Classifier: License :: OSI Approved :: MIT License
Classifier: Operating System :: OS Independent
Classifier: Topic :: Games/Entertainment
Classifier: Topic :: Games/Entertainment :: Role-Playing
Requires-Python: >=3.6
Requires-Dist: sly (>=0.3)
